{
    "genre": {
        "title" : "장르",
        "keywords" : [
            "현대판타지",
            "역사/시대물",
            "학원물",
            "캠퍼스물",
            "오피스물",
            "판타지/SF",
            "리얼물",
            "성인",
            "알파오메가물",
            "센티널가이드물",
            "취향소재",
            "수인물",
            "재회물",
            "짭근친"
        ]
    },
    "mood": {
        "title" : "분위기",
        "keywords" : [
            "피폐함",
            "잔잔함",
            "달달함",
            "노란장판",
            "삽질",
            "배틀호모",
            "청게"
        ]
    }
}